Workbook

Sheet prices
A1: Date | B1: AZN | C1: COST | D1: DTE | E1: RACE | F1: IBE | G1: JPM | H1: TYO:7974 | I1: NVDA | J1: RIO | K1: SIE | L1: KRX:000660 | M1: HKG:0700 | N1: WM | O1: WES | P1: HKG:1810 | Q1: WOSC | R1: EMXC | S1: BNDX | T1: TLT | U1: VGOV | V1: GLDM | W1: CMOP | X1: VNQ | Y1: DBMF | Z1: BTCGBP
A2: 43889 | B2: 6794 | C2: 281.1399 | D2: 14.776 | E2: 157.75 | F2: 8.3514 | G2: 116.11 | H2: 3627 | I2: 6.7518 | J2: 3608 | K2: 83.001 | L2: 87900 | M2: 355.836 | N2: 110.81 | O2: 40.65 | P2: 12.56 | Q2: 63.22 | R2: 44.8 | S2: 57.99 | T2: 155.31 | U2: 2522.001 | V2: 31.48 | W2: 1169.5 | X2: 87.33 | Y2: 25.0393 | Z2: 6759.914
A3: 43892 | B3: 7010 | C3: 309.1399 | D3: 14.876 | E3: 161.21 | F3: 8.6792 | G3: 121.52 | H3: 3709 | I3: 6.9107 | J3: 3720 | K3: 83.1 | L3: 92100 | M3: 359.155 | N3: 117.03 | O3: 40.6 | P3: 12.94 | Q3: 63.45 | R3: 45.4844 | S3: 57.9 | T3: 153.94 | U3: 2530.001 | V3: 31.62 | W3: 1191.75 | X3: 91.06 | Y3: 25.5507 | Z3: 7014.465
A4: 43893 | B4: 7172 | C4: 302.73 | D4: 14.666 | E4: 156.73 | F4: 8.7439 | G4: 116.96 | H4: 3680 | I4: 6.6472 | J4: 3821.5 | K4: 82.279 | L4: 92800 | M4: 363.211 | N4: 112.71 | O4: 40.3 | P4: 12.78 | Q4: 63.82 | R4: 45.2859 | S4: 58.05 | T4: 156.33 | U4: 2562 | V4: 32.62 | W4: 1203.5 | X4: 90.85 | Y4: 25.729 | Z4: 6817.199
A5: 43894 | B5: 7455 | C5: 320.74 | D5: 15.092 | E5: 160.38 | F5: 9.0595 | G5: 119.85 | H5: 3725 | I5: 7.1127 | J5: 3929 | K5: 83.632 | L5: 94300 | M5: 363.211 | N5: 120.29 | O5: 39.7 | P5: 12.94 | Q5: 64.31 | R5: 46.0549 | S5: 58.17 | T5: 154.67 | U5: 2548.626 | V5: 32.66 | W5: 1206 | X5: 94.28 | Y5: 26.0933 | Z5: 6783.145
A6: 43895 | B6: 7502 | C6: 315.76 | D6: 14.948 | E6: 154.19 | F6: 8.9503 | G6: 113.97 | H6: 3792 | I6: 6.8323 | J6: 3648.5 | K6: 80.718 | L6: 94900 | M6: 374.458 | N6: 117.71 | O6: 40.39 | P6: 13.1 | Q6: 63.46 | R6: 44.7577 | S6: 58.17 | T6: 158.52 | U6: 2568.25 | V6: 33.36 | W6: 1193 | X6: 92.26 | Y6: 25.9783 | Z6: 7030.238
A7: 43896 | B7: 7242 | C7: 311.3401 | D7: 14.674 | E7: 152.18 | F7: 8.574 | G7: 108.08 | H7: 3741 | I7: 6.651 | J7: 3505 | K7: 78.941 | L7: 92600 | M7: 364.87 | N7: 117.13 | O7: 39.2 | P7: 12.98 | Q7: 60.82 | R7: 44.0052 | S7: 58.4 | T7: 166.77 | U7: 2635.375 | V7: 33.38 | W7: 1148.5 | X7: 90.67 | Y7: 26.2047 | Z7: 7000.316
A8: 43899 | B8: 7003 | C8: 301.98 | D8: 13.518 | E8: 137.73 | F8: 8.0051 | G8: 93.44 | H8: 3593 | I8: 6.136 | J8: 3249 | K8: 71.453 | L8: 86900 | M8: 347.908 | N8: 112.07 | O8: 37.89 | P8: 12.06 | Q8: 56.01 | R8: 40.2523 | S8: 58.3 | T8: 171.29 | U8: 2675.001 | V8: 33.48 | W8: 1096.5 | X8: 83.68 | Y8: 25.4142 | Z8: 5984.066
A9: 43900 | B9: 6945 | C9: 309.3999 | D9: 13.488 | E9: 146.34 | F9: 7.5551 | G9: 100.7 | H9: 3619 | I9: 6.527 | J9: 3359 | K9: 74.159 | L9: 89100 | M9: 353.071 | N9: 113.46 | O9: 38.91 | P9: 12.04 | Q9: 55.33 | R9: 42.3489 | S9: 57.82 | T9: 162.51 | U9: 2664.501 | V9: 32.76 | W9: 1124.5 | X9: 86.54 | Y9: 25.6667 | Z9: 6198.949
A10: 43901 | B10: 6955 | C10: 297.4299 | D10: 12.85 | E10: 143.04 | F10: 7.6765 | G10: 95.96 | H10: 3547 | I10: 6.1617 | J10: 3364.5 | K10: 71.633 | L10: 85500 | M10: 348.83 | N10: 109.97 | O10: 37.5 | P10: 11.72 | Q10: 54.88 | R10: 40.32 | S10: 58.05 | T10: 156.53 | U10: 2631.126 | V10: 32.64 | W10: 1130.25 | X10: 81.34 | Y10: 25.2767 | Z10: 6131.016
A11: 43902 | B11: 6314 | C11: 279.8501 | D11: 11.75 | E11: 129.99 | F11: 6.597 | G11: 88.05 | H11: 3482 | I11: 5.4077 | J11: 2968 | K11: 63.351 | L11: 82800 | M11: 335.187 | N11: 97.74 | O11: 35.04 | P11: 11.1 | Q11: 49.91 | R11: 35.8438 | S11: 56.72 | T11: 157.5 | U11: 2614.251 | V11: 31.32 | W11: 1107.25 | X11: 73.1 | Y11: 24.29 | Z11: 4542.68
A12: 43903 | B12: 6316 | C12: 302.27 | D12: 11.758 | E12: 142.28 | F12: 6.9271 | G12: 103.91 | H12: 3322 | I12: 6.021 | J12: 3274 | K12: 64.416 | L12: 82500 | M12: 336.477 | N12: 105.32 | O12: 37.85 | P12: 10.98 | Q12: 49.255 | R12: 38.7102 | S12: 56.7 | T12: 153.94 | U12: 2517 | V12: 30.38 | W12: 1113.75 | X12: 79.48 | Y12: 24.9448 | Z12: 4427.512
A13: 43906 | B13: 6221 | C13: 283.1799 | D13: 10.85 | E13: 129.32 | F13: 6.6617 | G13: 88.36 | H13: 3295 | I13: 4.91 | J13: 3357.5 | K13: 58.497 | L13: 80600 | M13: 315.09 | N13: 99.89 | O13: 35.85 | P13: 10.2 | Q13: 46.88 | R13: 33.5649 | S13: 56.22 | T13: 163.91 | U13: 2530.625 | V13: 30.08 | W13: 1086 | X13: 65.39 | Y13: 24.88 | Z13: 3995.664
... A1307: 45716 | B1307: 11968 | C1307: 1048.61 | D1307: 34.81 | E1307: 464.5701 | F1307: 13.95 | G1307: 264.6499 | H1307: 11160 | I1307: 124.92 | J1307: 4794 | K1307: 219.55 | L1307: 190200 | M1307: 478.6 | N1307: 232.78 | O1307: 74.16 | P1307: 51.85 | Q1307: 102.52 | R1307: 54.58 | S1307: 49.5 | T1307: 92.43 | U1307: 1620.376 | V1307: 56.54 | W1307: 1922.001 | X1307: 93.9 | Y1307: 25.86 | Z1307: 66935.63

Sheet returns
A1: Date | B1: AZN | C1: COST | D1: DTE | E1: RACE | F1: IBE | G1: JPM | H1: TYO:7974 | I1: NVDA | J1: RIO | K1: SIE | L1: KRX:000660 | M1: HKG:0700 | N1: WM | O1: WES | P1: HKG:1810 | Q1: WOSC | R1: EMXC | S1: BNDX | T1: TLT | U1: VGOV | V1: GLDM | W1: CMOP | X1: VNQ | Y1: DBMF | Z1: BTCGBP
A2: 43892 | B2: =LN(prices!B3/prices!B2) -> 0.031297831 | C2: =LN(prices!C3/prices!C2) -> 0.094941515 | D2: =LN(prices!D3/prices!D2) -> 0.0067449332 | E2: =LN(prices!E3/prices!E2) -> 0.021696361 | F2: =LN(prices!F3/prices!F2) -> 0.038500169 | G2: =LN(prices!G3/prices!G2) -> 0.045540841 | H2: =LN(prices!H3/prices!H2) -> 0.022356438 | I2: =LN(prices!I3/prices!I2) -> 0.023261799 | ... Z2: =LN(prices!Z3/prices!Z2) -> 0.036964277
A3: 43893 | B3: =LN(prices!B4/prices!B3) -> 0.022846855 | C3: =LN(prices!C4/prices!C3) -> -0.020952606 | D3: =LN(prices!D4/prices!D3) -> -0.014217286 | E3: =LN(prices!E4/prices!E3) -> -0.028183283 | F3: =LN(prices!F4/prices!F3) -> 0.0074269559 | G3: =LN(prices!G4/prices!G3) -> -0.038246862 | H3: =LN(prices!H4/prices!H3) -> -0.0078495463 | I3: =LN(prices!I4/prices!I3) -> -0.038875222 | ... Z3: =LN(prices!Z4/prices!Z3) -> -0.028525762
A4: 43894 | B4: =LN(prices!B5/prices!B4) -> 0.038700392 | C4: =LN(prices!C5/prices!C4) -> 0.057789507 | D4: =LN(prices!D5/prices!D4) -> 0.028632912 | E4: =LN(prices!E5/prices!E4) -> 0.02302142 | F4: =LN(prices!F5/prices!F4) -> 0.035457616 | G4: =LN(prices!G5/prices!G4) -> 0.024408965 | H4: =LN(prices!H5/prices!H4) -> 0.0121541 | I4: =LN(prices!I5/prices!I4) -> 0.067686205 | ... Z4: =LN(prices!Z5/prices!Z4) -> -0.005007825
A5: 43895 | B5: =LN(prices!B6/prices!B5) -> 0.0062847034 | C5: =LN(prices!C6/prices!C5) -> -0.015648395 | D5: =LN(prices!D6/prices!D5) -> -0.0095872905 | E5: =LN(prices!E6/prices!E5) -> -0.039360391 | F5: =LN(prices!F6/prices!F5) -> -0.01212688 | G5: =LN(prices!G6/prices!G5) -> -0.050305705 | H5: =LN(prices!H6/prices!H5) -> 0.017826733 | I5: =LN(prices!I6/prices!I5) -> -0.040220552 | ... Z5: =LN(prices!Z6/prices!Z5) -> 0.035779701
A6: 43896 | B6: =LN(prices!B7/prices!B6) -> -0.03527224 | C6: =LN(prices!C7/prices!C6) -> -0.014096548 | D6: =LN(prices!D7/prices!D6) -> -0.018500291 | E6: =LN(prices!E7/prices!E6) -> -0.013121577 | F6: =LN(prices!F7/prices!F6) -> -0.042952683 | G6: =LN(prices!G7/prices!G6) -> -0.053063562 | H6: =LN(prices!H7/prices!H6) -> -0.013540629 | I6: =LN(prices!I7/prices!I6) -> -0.026894147 | ... Z6: =LN(prices!Z7/prices!Z6) -> -0.0042652693
A7: 43899 | B7: =LN(prices!B8/prices!B7) -> -0.033558783 | C7: =LN(prices!C8/prices!C7) -> -0.030525094 | D7: =LN(prices!D8/prices!D7) -> -0.08205509 | E7: =LN(prices!E8/prices!E7) -> -0.099768784 | F7: =LN(prices!F8/prices!F7) -> -0.06865553 | G7: =LN(prices!G8/prices!G7) -> -0.14555217 | H7: =LN(prices!H8/prices!H7) -> -0.040365447 | I7: =LN(prices!I8/prices!I7) -> -0.080594155 | ... Z7: =LN(prices!Z8/prices!Z7) -> -0.15685502
A8: 43900 | B8: =LN(prices!B9/prices!B8) -> -0.0083166525 | C8: =LN(prices!C9/prices!C8) -> 0.024273825 | D8: =LN(prices!D9/prices!D8) -> -0.0022217294 | E8: =LN(prices!E9/prices!E8) -> 0.060637435 | F8: =LN(prices!F9/prices!F8) -> -0.057856007 | G8: =LN(prices!G9/prices!G8) -> 0.074826281 | H8: =LN(prices!H9/prices!H8) -> 0.0072102365 | I8: =LN(prices!I9/prices!I8) -> 0.061774356 | ... Z8: =LN(prices!Z9/prices!Z8) -> 0.035279492
A9: 43901 | B9: =LN(prices!B10/prices!B9) -> 0.0014388492 | C9: =LN(prices!C10/prices!C9) -> -0.039456048 | D9: =LN(prices!D10/prices!D9) -> -0.04845659 | E9: =LN(prices!E10/prices!E9) -> -0.02280837 | F9: =LN(prices!F10/prices!F9) -> 0.015940882 | G9: =LN(prices!G10/prices!G9) -> -0.048214362 | H9: =LN(prices!H10/prices!H9) -> -0.020095569 | I9: =LN(prices!I10/prices!I9) -> -0.057594706 | ... Z9: =LN(prices!Z10/prices!Z9) -> -0.011019283
A10: 43902 | B10: =LN(prices!B11/prices!B10) -> -0.096691435 | C10: =LN(prices!C11/prices!C10) -> -0.060924464 | D10: =LN(prices!D11/prices!D10) -> -0.089490571 | E10: =LN(prices!E11/prices!E10) -> -0.095666787 | F10: =LN(prices!F11/prices!F10) -> -0.15154871 | G10: =LN(prices!G11/prices!G10) -> -0.086026603 | H10: =LN(prices!H11/prices!H10) -> -0.018495334 | I10: =LN(prices!I11/prices!I10) -> -0.13052885 | ... Z10: =LN(prices!Z11/prices!Z10) -> -0.29984333
A11: 43903 | B11: =LN(prices!B12/prices!B11) -> 0.00031670626 | C11: =LN(prices!C12/prices!C11) -> 0.077066555 | D11: =LN(prices!D12/prices!D11) -> 0.00068061939 | E11: =LN(prices!E12/prices!E11) -> 0.090339423 | F11: =LN(prices!F12/prices!F11) -> 0.048826255 | G11: =LN(prices!G12/prices!G11) -> 0.1656203 | H11: =LN(prices!H12/prices!H11) -> -0.04703983 | I11: =LN(prices!I12/prices!I11) -> 0.10742949 | ... Z11: =LN(prices!Z12/prices!Z11) -> -0.025679345
A12: 43906 | B12: =LN(prices!B13/prices!B12) -> -0.015155431 | C12: =LN(prices!C13/prices!C12) -> -0.065238273 | D12: =LN(prices!D13/prices!D12) -> -0.08036878 | E12: =LN(prices!E13/prices!E12) -> -0.095506994 | F12: =LN(prices!F13/prices!F12) -> -0.039066548 | G12: =LN(prices!G13/prices!G12) -> -0.16210576 | H12: =LN(prices!H13/prices!H12) -> -0.0081608432 | I12: =LN(prices!I13/prices!I12) -> -0.20397942 | ... Z12: =LN(prices!Z13/prices!Z12) -> -0.10262803
A13: 43907 | B13: =LN(prices!B14/prices!B13) -> 0.077306287 | C13: =LN(prices!C14/prices!C13) -> 0.080732789 | D13: =LN(prices!D14/prices!D13) -> 0.059919575 | E13: =LN(prices!E14/prices!E13) -> 0.054840198 | F13: =LN(prices!F14/prices!F13) -> 0.096064548 | G13: =LN(prices!G14/prices!G13) -> 0.059318947 | H13: =LN(prices!H14/prices!H13) -> 0.056922338 | I13: =LN(prices!I14/prices!I13) -> 0.10097822 | ... Z13: =LN(prices!Z14/prices!Z13) -> 0.12722835
... A1306: 45716 | B1306: =LN(prices!B1307/prices!B1306) -> -0.0041691047 | C1306: =LN(prices!C1307/prices!C1306) -> 0.025987783 | D1306: =LN(prices!D1307/prices!D1306) -> 0.011848137 | E1306: =LN(prices!E1307/prices!E1306) -> 0.0087996061 | F1306: =LN(prices!F1307/prices!F1306) -> 0.010810916 | G1306: =LN(prices!G1307/prices!G1306) -> 0.021386727 | H1306: =LN(prices!H1307/prices!H1306) -> -0.021277398 | I1306: =LN(prices!I1307/prices!I1306) -> 0.03893257 | ... Z1306: =LN(prices!Z1307/prices!Z1306) -> 0.0007557875

Sheet portfolio
A1: Date | B1: AZN | C1: COST | D1: DTE | E1: RACE | F1: TYO:7974 | G1: NVDA | H1: SIE | I1: WM | J1: WES | K1: HKG:1810 | L1: BNDX | M1: GLDM | N1: CMOP | O1: BTCGBP
A2: 43892 | B2: 0.031297831 | C2: 0.094941515 | D2: 0.0067449332 | E2: 0.021696361 | F2: 0.022356438 | G2: 0.023261799 | H2: 0.0011920459 | I2: 0.054613289 | J2: -0.0012307694 | K2: 0.029806128 | L2: -0.0015531973 | M2: 0.0044374082 | N2: 0.018846508 | O2: 0.036964277
A3: 43893 | B3: 0.022846855 | C3: -0.020952606 | D3: -0.014217286 | E3: -0.028183283 | F3: -0.0078495463 | G3: -0.038875222 | H3: -0.0099287908 | I3: -0.037612164 | J3: -0.0074165977 | K3: -0.01244184 | L3: 0.0025873236 | M3: 0.031135765 | N3: 0.0098111631 | O3: -0.028525762
A4: 43894 | B4: 0.038700392 | C4: 0.057789507 | D4: 0.028632912 | E4: 0.02302142 | F4: 0.0121541 | G4: 0.067686205 | H4: 0.016310311 | I4: 0.065087346 | J4: -0.015000281 | K4: 0.01244184 | L4: 0.0020650498 | M4: 0.0012254903 | N4: 0.0020751201 | O4: -0.005007825
A5: 43895 | B5: 0.0062847034 | C5: -0.015648395 | D5: -0.0095872905 | E5: -0.039360391 | F5: 0.017826733 | G5: -0.040220552 | H5: -0.035464623 | I5: -0.021681522 | J5: 0.017231042 | K5: 0.012288941 | L5: 0 | M5: 0.02120649 | N5: -0.010837955 | O5: 0.035779701
A6: 43896 | B6: -0.03527224 | C6: -0.014096548 | D6: -0.018500291 | E6: -0.013121577 | F6: -0.013540629 | G6: -0.026894147 | H6: -0.022260861 | I6: -0.0049395433 | J6: -0.029905483 | K6: -0.0092025189 | L6: 0.0039461319 | M6: 0.00059934074 | N6: -0.0380144 | O6: -0.0042652693
A7: 43899 | B7: -0.033558783 | C7: -0.030525094 | D7: -0.08205509 | E7: -0.099768784 | F7: -0.040365447 | G7: -0.080594155 | H7: -0.099660847 | I7: -0.044160753 | J7: -0.033989522 | K7: -0.07351552 | L7: -0.0017137965 | M7: 0.0029913274 | N7: -0.046333454 | O7: -0.15685502
A8: 43900 | B8: -0.0083166525 | C8: 0.024273825 | D8: -0.0022217294 | E8: 0.060637435 | F8: 0.0072102365 | G8: 0.061774356 | H8: 0.037171546 | I8: 0.012326676 | J8: 0.026564062 | K8: -0.0016597514 | L8: -0.0082673568 | M8: -0.021739987 | N8: 0.025215204 | O8: 0.035279492
A9: 43901 | B9: 0.0014388492 | C9: -0.039456048 | D9: -0.04845659 | E9: -0.02280837 | F9: -0.020095569 | G9: -0.057594706 | H9: -0.034655575 | I9: -0.031242751 | J9: -0.036910354 | K9: -0.026937656 | L9: 0.0039699716 | M9: -0.0036697289 | N9: 0.0051003548 | O9: -0.011019283
A10: 43902 | B10: -0.096691435 | C10: -0.060924464 | D10: -0.089490571 | E10: -0.095666787 | F10: -0.018495334 | G10: -0.13052885 | H10: -0.12286517 | I10: -0.11789671 | J10: -0.067850667 | K10: -0.054351676 | L10: -0.023177826 | M10: -0.041281659 | N10: -0.020559383 | O10: -0.29984333
A11: 43903 | B11: 0.00031670626 | C11: 0.077066555 | D11: 0.00068061939 | E11: 0.090339423 | F11: -0.04703983 | G11: 0.10742949 | H11: 0.016671357 | I11: 0.074692443 | J11: 0.077140714 | K11: -0.010869672 | L11: -0.00035267149 | M11: -0.030472374 | N11: 0.005853236 | O11: -0.025679345
A12: 43906 | B12: -0.015155431 | C12: -0.065238273 | D12: -0.08036878 | E12: -0.095506994 | F12: -0.0081608432 | G12: -0.20397942 | H12: -0.096386579 | I12: -0.052933754 | J12: -0.054287413 | K12: -0.073687716 | L12: -0.0085016453 | M12: -0.0099239981 | N12: -0.025231478 | O12: -0.10262803
A13: 43907 | B13: 0.077306287 | C13: 0.080732789 | D13: 0.059919575 | E13: 0.054840198 | F13: 0.056922338 | G13: 0.10097822 | H13: 0.035005842 | I13: 0.086635894 | J13: 0.057189407 | K13: -0.0058997221 | L13: 0.00053347561 | M13: 0.013210232 | N13: 0.010305828 | O13: 0.12722835
... A1306: 45716 | B1306: -0.0041691047 | C1306: 0.025987783 | D1306: 0.011848137 | E1306: 0.0087996061 | F1306: -0.021277398 | G1306: 0.03893257 | H1306: 0.0073143183 | I1306: 0.013711584 | J1306: -0.0077905028 | K1306: -0.023821994 | L1306: 0.0034402543 | M1306: -0.0065227203 | N1306: -0.012409667 | O1306: 0.0007557875

Sheet weights
A1: AZN | B1: COST | C1: DTE | D1: RACE | E1: TYO:7974 | F1: NVDA | G1: SIE | H1: WM | I1: WES | J1: HKG:1810 | K1: BNDX | L1: GLDM | M1: CMOP | N1: BTCGBP
A2: 0.077876775 | B2: 0.12211813 | C2: 0.12211813 | D2: 0.010168862 | E2: 0.024835106 | F2: 0.065854567 | G2: 0.016985897 | H2: 0.073885864 | I2: 0.065318836 | J2: 0.031428459 | K2: 0.15 | L2: 0.1240396 | M2: 0.061392645 | N2: 0.053977119

Sheet statistics
B1: AZN | C1: COST | D1: DTE | E1: RACE | F1: IBE | G1: JPM | H1: TYO:7974 | I1: NVDA | J1: RIO | K1: SIE | L1: KRX:000660 | M1: HKG:0700 | N1: WM | O1: WES | P1: HKG:1810 | Q1: WOSC | R1: EMXC | S1: BNDX | T1: TLT | U1: VGOV | V1: GLDM | W1: CMOP | X1: VNQ | Y1: DBMF | Z1: BTCGBP
A2: Mean | B2: 0.00043386709 | C2: 0.0010087114 | D2: 0.0006566287 | E2: 0.00082766357 | F2: 0.00039314201 | G2: 0.00063131786 | H2: 0.00086124912 | I2: 0.0022359114 | J2: 0.00021778662 | K2: 0.00074538494 | L2: 0.00059147613 | M2: 0.00022712278 | N2: 0.00056879447 | O2: 0.00046070964 | P2: 0.0010864657 | Q2: 0.00037044996 | R2: 0.00015130987 | S2: -0.00012130108 | T2: -0.00039767932 | U2: -0.00033899955 | V2: 0.00044873251 | W2: 0.00038068239 | X2: 5.5583402e-05 | Y2: 2.4713244e-05 | Z2: 0.0017568745
A3: Standard Err. | B3: 0.00042737579 | C3: 0.00041269847 | D3: 0.00036262362 | E3: 0.00051673193 | F3: 0.00038308362 | G3: 0.0005537548 | H3: 0.00048438787 | I3: 0.00093030954 | J3: 0.00053129085 | K3: 0.00051361157 | L3: 0.00068036398 | M3: 0.00069047591 | N3: 0.00038658082 | O3: 0.00040161044 | P3: 0.00078904847 | Q3: 0.00033970428 | R3: 0.00036641837 | S3: 9.3027725e-05 | T3: 0.00030658696 | U3: 0.00020903891 | V3: 0.0002644136 | W3: 0.00027429229 | X3: 0.00043975901 | Y3: 0.00023916739 | Z3: 0.0010503323
A4: Median | B4: 0.00030656039 | C4: 0.00081162091 | D4: 0.00073737253 | E4: 0.00070692197 | F4: 0 | G4: 0.00026379424 | H4: 0 | I4: 0.0021083617 | J4: 0 | K4: 0.00075145598 | L4: 0 | M4: 0 | N4: 0.00041474846 | O4: 0.00055233362 | P4: 0 | Q4: 0.00064322472 | R4: 0 | S4: 0 | T4: 0 | U4: -0.00015142142 | V4: 0.00026677338 | W4: 0 | X4: 0 | Y4: 0.00036556389 | Z4: 0.0010732007
A5: Mode | B5: 0 | C5: 0 | D5: 0 | E5: 0 | F5: 0 | G5: 0 | H5: 0 | I5: 0 | J5: 0 | K5: 0 | L5: 0 | M5: 0 | N5: 0 | O5: 0 | P5: 0 | Q5: 0 | R5: 0 | S5: 0 | T5: 0 | U5: 0 | V5: 0 | W5: 0 | X5: 0 | Y5: 0 | Z5: #N/A
A6: Standard Dev. | B6: 0.015438858 | C6: 0.014908643 | D6: 0.0130997 | E6: 0.018666829 | F6: 0.013838813 | G6: 0.020004272 | H6: 0.017498407 | I6: 0.033607231 | J6: 0.019192767 | K6: 0.018554107 | L6: 0.024578002 | M6: 0.024943293 | N6: 0.013965148 | O6: 0.01450809 | P6: 0.028504205 | Q6: 0.012271744 | R6: 0.013236784 | S6: 0.0033606065 | T6: 0.011075388 | U6: 0.0075514855 | V6: 0.009551884 | W6: 0.0099087495 | X6: 0.015886199 | Y6: 0.0086398703 | Z6: 0.037943025
A7: Sample Var. | B7: 0.00023835833 | C7: 0.00022226763 | D7: 0.00017160214 | E7: 0.00034845051 | F7: 0.00019151274 | G7: 0.00040017092 | H7: 0.00030619424 | I7: 0.001129446 | J7: 0.00036836231 | K7: 0.00034425488 | L7: 0.00060407817 | M7: 0.00062216786 | N7: 0.00019502537 | O7: 0.00021048469 | P7: 0.00081248972 | Q7: 0.0001505957 | R7: 0.00017521246 | S7: 1.1293676e-05 | T7: 0.00012266421 | U7: 5.7024933e-05 | V7: 9.1238488e-05 | W7: 9.8183317e-05 | X7: 0.00025237133 | Y7: 7.4647359e-05 | Z7: 0.0014396732
A8: Kurtosis | B8: 4.6928133 | C8: 9.721339 | D8: 8.3328161 | E8: 5.7792169 | F8: 14.723572 | G8: 13.31222 | H8: 12.373808 | I8: 4.1134785 | J8: 4.9741046 | K8: 5.13601 | L8: 2.1811503 | M8: 6.4111565 | N8: 12.009526 | O8: 7.98965 | P8: 1.9939453 | Q8: 7.6161222 | R8: 21.215664 | S8: 13.060785 | T8: 4.3630576 | U8: 13.743549 | V8: 2.6930983 | W8: 3.510435 | X8: 23.10409 | Y8: 13.075889 | Z8: 6.1504848
A9: Skewness | B9: -0.32660796 | C9: -0.34289939 | D9: -0.73483772 | E9: 0.14804639 | F9: -0.86594552 | G9: 0.0039110111 | H9: -0.78561041 | I9: 0.01146325 | J9: -0.041041305 | K9: -0.52328542 | L9: 0.16534649 | M9: 0.432782 | N9: -0.56487473 | O9: -0.52946303 | P9: 0.33432385 | Q9: -0.67286582 | R9: -1.86675 | S9: -1.4590524 | T9: 0.11944229 | U9: 0.95587342 | V9: -0.34004798 | W9: -0.31296987 | X9: -1.6141651 | Y9: -1.7295822 | Z9: -0.50214575
A10: Range | B10: 0.17399772 | C10: 0.22791698 | D10: 0.18067311 | E10: 0.21829703 | F10: 0.24761326 | G10: 0.32772607 | H10: 0.30833623 | I10: 0.42206731 | J10: 0.26248463 | K10: 0.21125584 | L10: 0.23555268 | M10: 0.34006261 | N10: 0.2045326 | O10: 0.21124799 | P10: 0.26116501 | Q10: 0.17639895 | R10: 0.21955478 | S10: 0.044203006 | T10: 0.14151288 | U10: 0.12071645 | V10: 0.1017609 | W10: 0.10182514 | X10: 0.28128314 | Y10: 0.11916979 | Z10: 0.47432098
A11: Minimum | B11: -0.096691435 | C11: -0.13297546 | D11: -0.089490571 | E11: -0.099768784 | F11: -0.15154871 | G11: -0.16210576 | H11: -0.18063 | I11: -0.20397942 | J11: -0.12539104 | K11: -0.12286517 | L11: -0.10979639 | M11: -0.13179631 | N11: -0.11789671 | O11: -0.10430733 | P11: -0.10825734 | Q11: -0.0949276 | R11: -0.14262225 | S11: -0.030946805 | T11: -0.069010303 | U11: -0.043775371 | V11: -0.054508017 | W11: -0.050336161 | X11: -0.19513608 | Y11: -0.089169779 | Z11: -0.29984333
A12: Maximum | B12: 0.077306287 | C12: 0.094941515 | D12: 0.09118254 | E12: 0.11852824 | F12: 0.096064548 | G12: 0.1656203 | H12: 0.12770623 | I12: 0.2180879 | J12: 0.13709359 | K12: 0.088390671 | L12: 0.12575629 | M12: 0.2082663 | N12: 0.086635894 | O12: 0.10694066 | P12: 0.15290767 | Q12: 0.081471354 | R12: 0.076932522 | S12: 0.013256201 | T12: 0.072502576 | U12: 0.076941078 | V12: 0.047252885 | W12: 0.051488981 | X12: 0.086147066 | Y12: 0.030000011 | Z12: 0.17447765
A13: Sum | B13: 0.56619655 | C13: 1.3163683 | D13: 0.85690046 | E13: 1.080101 | F13: 0.51305032 | G13: 0.8238698 | H13: 1.1239301 | I13: 2.9178644 | J13: 0.28421153 | K13: 0.97272734 | L13: 0.77187635 | M13: 0.29639522 | N13: 0.74227678 | O13: 0.60122609 | P13: 1.4178378 | Q13: 0.48343719 | R13: 0.19745938 | S13: -0.15829791 | T13: -0.51897152 | U13: -0.44239441 | V13: 0.58559593 | W13: 0.49679052 | X13: 0.07253634 | Y13: 0.032250783 | Z13: 2.2927212
A14: Count | B14: 1305 | C14: 1305 | D14: 1305 | E14: 1305 | F14: 1305 | G14: 1305 | H14: 1305 | I14: 1305 | J14: 1305 | K14: 1305 | L14: 1305 | M14: 1305 | N14: 1305 | O14: 1305 | P14: 1305 | Q14: 1305 | R14: 1305 | S14: 1305 | T14: 1305 | U14: 1305 | V14: 1305 | W14: 1305 | X14: 1305 | Y14: 1305 | Z14: 1305

Sheet correlations
B1: AZN | C1: COST | D1: DTE | E1: RACE | F1: IBE | G1: JPM | H1: TYO:7974 | I1: NVDA | J1: RIO | K1: SIE | L1: KRX:000660 | M1: HKG:0700 | N1: WM | O1: WES | P1: HKG:1810 | Q1: WOSC | R1: EMXC | S1: BNDX | T1: TLT | U1: VGOV | V1: GLDM | W1: CMOP | X1: VNQ | Y1: DBMF | Z1: BTCGBP
A2: AZN | B2: 1
A3: COST | B3: 0.13032291 | C3: 1
A4: DTE | B4: 0.22390546 | C4: 0.23627705 | D4: 1
A5: RACE | B5: 0.15679929 | C5: 0.4414108 | D5: 0.34117343 | E5: 1
A6: IBE | B6: 0.32287573 | C6: 0.20795484 | D6: 0.42433482 | E6: 0.2961044 | F6: 1
A7: JPM | B7: 0.06713499 | C7: 0.29807088 | D7: 0.41063979 | E7: 0.45416371 | F7: 0.29783831 | G7: 1
A8: TYO:7974 | B8: 0.056601656 | C8: 0.048865127 | D8: 0.087442552 | E8: 0.07719729 | F8: 0.057963021 | G8: 0.054974168 | H8: 1
A9: NVDA | B9: 0.081340983 | C9: 0.47064725 | D9: 0.21578809 | E9: 0.51507492 | F9: 0.16569262 | G9: 0.32365331 | H9: 0.087184466 | I9: 1
A10: RIO | B10: 0.14488668 | C10: 0.090600604 | D10: 0.195525 | E10: 0.25242904 | F10: 0.24497205 | G10: 0.329305 | H10: 0.08994112 | I10: 0.17710827 | J10: 1
A11: SIE | B11: 0.19604274 | C11: 0.23788753 | D11: 0.4663792 | E11: 0.44124704 | F11: 0.37340558 | G11: 0.49817993 | H11: 0.083736998 | I11: 0.39206712 | J11: 0.36459042 | K11: 1
A12: KRX:000660 | B12: 0.03880836 | C12: 0.030205014 | D12: 0.074565693 | E12: 0.11121804 | F12: 0.068667211 | G12: 0.16624366 | H12: 0.22622397 | I12: 0.15801085 | J12: 0.22520017 | K12: 0.18171696 | L12: 1
A13: HKG:0700 | B13: 0.027931595 | C13: 0.012831441 | D13: 0.058003212 | E13: 0.14519897 | F13: 0.063950894 | G13: 0.12017532 | H13: 0.1535284 | I13: 0.12368433 | J13: 0.26379633 | K13: 0.17635558 | L13: 0.25205016 | M13: 1
A14: WM | B14: 0.18918331 | C14: 0.42309029 | D14: 0.33701657 | E14: 0.3959472 | F14: 0.33418332 | G14: 0.48287656 | H14: 0.056856224 | I14: 0.22763389 | J14: 0.21014204 | K14: 0.27575449 | L14: 0.077791591 | M14: 0.015008819 | N14: 1
A15: WES | B15: 0.13679545 | C15: 0.18914443 | D15: 0.2131079 | E15: 0.23965037 | F15: 0.21667742 | G15: 0.29863023 | H15: 0.20332594 | I15: 0.18111406 | J15: 0.15705526 | K15: 0.241902 | L15: 0.25818081 | M15: 0.17873081 | N15: 0.23363523 | O15: 1
A16: HKG:1810 | B16: 0.034032769 | C16: 0.023340651 | D16: 0.036716047 | E16: 0.13219071 | F16: 0.066545474 | G16: 0.096599038 | H16: 0.14366534 | I16: 0.12201409 | J16: 0.24250268 | K16: 0.15570015 | L16: 0.26998715 | M16: 0.58633687 | N16: 0.0094407066 | O16: 0.16201978 | P16: 1
A17: WOSC | B17: 0.21050785 | C17: 0.21265544 | D17: 0.43175108 | E17: 0.396994 | F17: 0.44780609 | G17: 0.52583387 | H17: 0.13543684 | I17: 0.32323918 | J17: 0.44359892 | K17: 0.61345161 | L17: 0.25764779 | M17: 0.22578328 | N17: 0.35880318 | O17: 0.29241589 | P17: 0.22868333 | Q17: 1
A18: EMXC | B18: 0.15007927 | C18: 0.41093914 | D18: 0.415681 | E18: 0.61657309 | F18: 0.38765056 | G18: 0.63828114 | H18: 0.092720184 | I18: 0.57159391 | J18: 0.45009064 | K18: 0.59120412 | L18: 0.28741954 | M18: 0.26390808 | N18: 0.43330795 | O18: 0.33172474 | P18: 0.24266865 | Q18: 0.56955431 | R18: 1
A19: BNDX | B19: 0.080715036 | C19: 0.1396457 | D19: 0.077896932 | E19: 0.16317865 | F19: 0.20582369 | G19: 0.0194649 | H19: -0.026320859 | I19: 0.1401304 | J19: -0.0089593022 | K19: 0.07471223 | L19: -0.0024586585 | M19: 0.049929507 | N19: 0.13465068 | O19: 0.073200178 | P19: -0.00020537906 | Q19: 0.10896372 | R19: 0.19098236 | S19: 1
A20: TLT | B20: -0.033627237 | C20: -0.041919126 | D20: -0.087148552 | E20: -0.033610009 | F20: 0.0087886075 | G20: -0.26452655 | H20: -0.025950143 | I20: -0.024389292 | J20: -0.13622206 | K20: -0.10342963 | L20: -0.05296412 | M20: -0.027566329 | N20: -0.10406565 | O20: -0.1077144 | P20: -0.065633664 | Q20: -0.093901785 | R20: -0.1062321 | S20: 0.63556179 | T20: 1
A21: VGOV | B21: 0.059136191 | C21: 0.044263422 | D21: 0.0058171317 | E21: 0.042701908 | F21: 0.072605808 | G21: -0.13557565 | H21: -0.022450859 | I21: 0.038380515 | J21: -0.10389895 | K21: -0.03863395 | L21: -0.027805631 | M21: -0.035777122 | N21: -0.0053877042 | O21: -0.028065263 | P21: -0.041651158 | Q21: -0.012895262 | R21: -0.0038360727 | S21: 0.59855688 | T21: 0.57962601 | U21: 1
A22: GLDM | B22: 0.025105544 | C22: 0.12106995 | D22: 0.010017103 | E22: 0.13578928 | F22: 0.090725988 | G22: -0.020566511 | H22: 0.038225867 | I22: 0.14349766 | J22: 0.17080556 | K22: 0.090508878 | L22: 0.064640568 | M22: 0.086604778 | N22: 0.093060473 | O22: -0.00068411849 | P22: 0.062142377 | Q22: 0.064541303 | R22: 0.26410212 | S22: 0.2889254 | T22: 0.26324324 | U22: 0.20235295 | V22: 1
A23: CMOP | B23: 0.044122618 | C23: 0.021383621 | D23: 0.073515474 | E23: -0.012540741 | F23: 0.019570923 | G23: 0.096405749 | H23: 0.063730255 | I23: 0.050365244 | J23: 0.33460145 | K23: 0.069972904 | L23: 0.058666754 | M23: 0.10757299 | N23: 0.053219758 | O23: 0.060791056 | P23: 0.10057601 | Q23: 0.18452114 | R23: 0.13294753 | S23: -0.063480464 | T23: -0.1593345 | U23: -0.10228913 | V23: 0.1900406 | W23: 1
A24: VNQ | B24: 0.13739268 | C24: 0.44657843 | D24: 0.39944062 | E24: 0.54013126 | F24: 0.39026329 | G24: 0.63551298 | H24: 0.048863966 | I24: 0.40060924 | J24: 0.25438181 | K24: 0.44438233 | L24: 0.13687322 | M24: 0.10806591 | N24: 0.58776957 | O24: 0.29369067 | P24: 0.10027625 | Q24: 0.52290955 | R24: 0.69178373 | S24: 0.27859381 | T24: -0.0091835683 | U24: 0.094270604 | V24: 0.17023237 | W24: 0.053009407 | X24: 1
A25: DBMF | B25: 0.011016515 | C25: 0.069940984 | D25: 0.099202328 | E25: 0.020654555 | F25: 0.0067291893 | G25: 0.093683948 | H25: 0.11153781 | I25: 0.078820847 | J25: 0.14458614 | K25: 0.093884146 | L25: 0.060339522 | M25: 0.017532878 | N25: 0.06288944 | O25: 0.051310777 | P25: 0.044620267 | Q25: 0.1395321 | R25: 0.13310751 | S25: -0.27187657 | T25: -0.28825128 | U25: -0.2093988 | V25: 0.048190542 | W25: 0.23835112 | X25: 0.021690244 | Y25: 1
A26: BTCGBP | B26: 0.084143107 | C26: 0.22540549 | D26: 0.20138094 | E26: 0.22358732 | F26: 0.1608277 | G26: 0.22985473 | H26: 0.1051739 | I26: 0.30843311 | J26: 0.16736134 | K26: 0.23720151 | L26: 0.040894361 | M26: 0.059777968 | N26: 0.16194043 | O26: 0.10843221 | P26: 0.047708601 | Q26: 0.24840415 | R26: 0.30034147 | S26: 0.078441561 | T26: -0.063615409 | U26: -0.00076682034 | V26: 0.10049957 | W26: 0.13088676 | X26: 0.24674367 | Y26: 0.11020104 | Z26: 1

Sheet covariances
B1: AZN | C1: COST | D1: DTE | E1: RACE | F1: IBE | G1: JPM | H1: TYO:7974 | I1: NVDA | J1: RIO | K1: SIE | L1: KRX:000660 | M1: HKG:0700 | N1: WM | O1: WES | P1: HKG:1810 | Q1: WOSC | R1: EMXC | S1: BNDX | T1: TLT | U1: VGOV | V1: GLDM | W1: CMOP | X1: VNQ | Y1: DBMF | Z1: BTCGBP
A2: AZN | B2: =VARP(returns!$B$2:$B$1306) -> 0.00023817568 | C2: {=TRANSPOSE(B3:B26)} -> 2.9973753e-05 | D2: 4.5248926e-05 | E2: 4.5154069e-05 | F2: 6.8931303e-05 | G2: 2.0718292e-05 | H2: 1.5279526e-05 | I2: 4.2172019e-05 | J2: 4.2899111e-05 | K2: 5.6114237e-05 | L2: 1.4714791e-05 | M2: 1.0748102e-05 | N2: 4.075779e-05 | O2: 3.0617108e-05 | P2: 1.4965405e-05 | Q2: 3.9852615e-05 | R2: 3.0646822e-05 | S2: 4.1846038e-06 | T2: -5.7455601e-06 | U2: 6.8891872e-06 | V2: 3.6994821e-06 | W2: 6.7446958e-06 | X2: 3.3671762e-05 | Y2: 1.4683639e-06 | Z2: 4.9253007e-05
A3: COST | B3: 2.9973753e-05 | C3: =VARP(returns!$C$2:$C$1306) -> 0.00022209731 | D3: {=TRANSPOSE(C4:C26)} -> 4.6109252e-05 | E3: 0.00012274921 | F3: 4.2871932e-05 | G3: 8.8827514e-05 | H3: 1.2738044e-05 | I3: 0.00023563155 | J3: 2.590442e-05 | K3: 6.5753205e-05 | L3: 1.1059381e-05 | M3: 4.7679797e-06 | N3: 8.8020495e-05 | O3: 4.0879822e-05 | P3: 9.9112196e-06 | Q3: 3.8876573e-05 | R3: 8.1033612e-05 | S3: 6.9911787e-06 | T3: -6.9163401e-06 | U3: 4.9794636e-06 | V3: 1.7227831e-05 | W3: 3.1564963e-06 | X3: 0.00010568733 | Y3: 9.0021066e-06 | Z3: 0.00012740945
A4: DTE | B4: 4.5248926e-05 | C4: 4.6109252e-05 | D4: =VARP(returns!$D$2:$D$1306) -> 0.00017147064 | E4: {=TRANSPOSE(D5:D26)} -> 8.3363162e-05 | F4: 7.6866293e-05 | G4: 0.00010752568 | H4: 2.0028562e-05 | I4: 9.4926755e-05 | J4: 4.9121125e-05 | K4: 0.00011326811 | L4: 2.3989106e-05 | M4: 1.8938006e-05 | N4: 6.1606316e-05 | O4: 4.0470468e-05 | P4: 1.3699139e-05 | Q4: 6.9353461e-05 | R4: 7.2022981e-05 | S4: 3.4266239e-06 | T4: -1.2634194e-05 | U4: 5.7500248e-07 | V4: 1.2524477e-06 | W4: 9.5351173e-06 | X4: 8.306167e-05 | Y4: 1.1219087e-05 | Z4: 0.00010001814
A5: RACE | B5: 4.5154069e-05 | C5: 0.00012274921 | D5: 8.3363162e-05 | E5: =VARP(returns!$E$2:$E$1306) -> 0.0003481835 | F5: {=TRANSPOSE(E6:E26)} -> 7.6433075e-05 | G5: 0.00016946219 | H5: 2.5196383e-05 | I5: 0.00032287972 | J5: 9.0367974e-05 | K5: 0.00015270719 | L5: 5.0986999e-05 | M5: 6.7554604e-05 | N5: 0.00010313842 | O5: 6.4852392e-05 | P5: 7.0282549e-05 | Q5: 9.0871532e-05 | R5: 0.00015223156 | S5: 1.0228657e-05 | T5: -6.9432882e-06 | U5: 6.0147461e-06 | V5: 2.4193135e-05 | W5: -2.3178198e-06 | X5: 0.00016005047 | Y5: 3.328593e-06 | Z5: 0.00015824018
A6: IBE | B6: 6.8931303e-05 | C6: 4.2871932e-05 | D6: 7.6866293e-05 | E6: 7.6433075e-05 | F6: =VARP(returns!$F$2:$F$1306) -> 0.00019136599 | G6: {=TRANSPOSE(F7:F26)} -> 8.2389001e-05 | H6: 1.4025406e-05 | I6: 7.7001965e-05 | J6: 6.5015969e-05 | K6: 9.5804693e-05 | L6: 2.3337907e-05 | M6: 2.205801e-05 | N6: 6.4535139e-05 | O6: 4.3470019e-05 | P6: 2.6229703e-05 | Q6: 7.5991006e-05 | R6: 7.0955951e-05 | S6: 9.5648669e-06 | T6: 1.3459996e-06 | U6: 7.5817538e-06 | V6: 1.1983582e-05 | W6: 2.6816128e-06 | X6: 8.5732133e-05 | Y6: 8.0396268e-07 | Z6: 8.4383731e-05
A7: JPM | B7: 2.0718292e-05 | C7: 8.8827514e-05 | D7: 0.00010752568 | E7: 0.00016946219 | F7: 8.2389001e-05 | G7: =VARP(returns!$G$2:$G$1306) -> 0.00039986427 | H7: {=TRANSPOSE(G8:G26)} -> 1.9228571e-05 | I7: 0.00021742157 | J7: 0.0001263356 | K7: 0.00018476348 | L7: 8.1673564e-05 | M7: 5.991822e-05 | N7: 0.0001347943 | O7: 8.6603184e-05 | P7: 5.5039132e-05 | Q7: 0.00012898663 | R7: 0.00016888238 | S7: 1.3075541e-06 | T7: -5.8562289e-05 | U7: -2.0464631e-05 | V7: -3.9268064e-06 | W7: 1.9094647e-05 | X7: 0.00020180609 | Y7: 1.6179394e-05 | Z7: 0.00017433125
A8: TYO:7974 | B8: 1.5279526e-05 | C8: 1.2738044e-05 | D8: 2.0028562e-05 | E8: 2.5196383e-05 | F8: 1.4025406e-05 | G8: 1.9228571e-05 | H8: =VARP(returns!$H$2:$H$1306) -> 0.00030595961 | I8: {=TRANSPOSE(H9:H26)} -> 5.1231542e-05 | J8: 3.0182935e-05 | K8: 2.7165833e-05 | L8: 9.7218918e-05 | M8: 6.6958869e-05 | N8: 1.3883186e-05 | O8: 5.1578492e-05 | P8: 7.1602226e-05 | Q8: 2.9060875e-05 | R8: 2.1459637e-05 | S8: -1.5466189e-06 | T8: -5.0253266e-06 | U8: -2.9643599e-06 | V8: 6.3842807e-06 | W8: 1.1041551e-05 | X8: 1.3572952e-05 | Y8: 1.6849807e-05 | Z8: 6.977591e-05
A9: NVDA | B9: 4.2172019e-05 | C9: 0.00023563155 | D9: 9.4926755e-05 | E9: 0.00032287972 | F9: 7.7001965e-05 | G9: 0.00021742157 | H9: 5.1231542e-05 | I9: =VARP(returns!$I$2:$I$1306) -> 0.0011285805 | J9: {=TRANSPOSE(I10:I26)} -> 0.00011415009 | K9: 0.00024428696 | L9: 0.00013041673 | M9: 0.00010360203 | N9: 0.00010675354 | O9: 8.8239334e-05 | P9: 0.00011679351 | Q9: 0.00013320793 | R9: 0.00025407966 | S9: 1.5814294e-05 | T9: -9.0710577e-06 | U9: 9.7329165e-06 | V9: 4.6029224e-05 | W9: 1.6759058e-05 | X9: 0.00021371784 | Y9: 2.286905e-05 | Z9: 0.00039300019
A10: RIO | B10: 4.2899111e-05 | C10: 2.590442e-05 | D10: 4.9121125e-05 | E10: 9.0367974e-05 | F10: 6.5015969e-05 | G10: 0.0001263356 | H10: 3.0182935e-05 | I10: 0.00011415009 | J10: =VARP(returns!$J$2:$J$1306) -> 0.00036808004 | K10: {=TRANSPOSE(J11:J26)} -> 0.00012973286 | L10: 0.00010614999 | M10: 0.00012619066 | N10: 5.6281177e-05 | O10: 4.3698589e-05 | P10: 0.00013256539 | Q10: 0.00010440022 | R10: 0.00011425814 | S10: -5.7742624e-07 | T10: -2.8934172e-05 | U10: -1.5046942e-05 | V10: 3.128929e-05 | W10: 6.3584512e-05 | X10: 7.7501612e-05 | Y10: 2.3957338e-05 | Z10: 0.00012178443
A11: SIE | B11: 5.6114237e-05 | C11: 6.5753205e-05 | D11: 0.00011326811 | E11: 0.00015270719 | F11: 9.5804693e-05 | G11: 0.00018476348 | H11: 2.7165833e-05 | I11: 0.00024428696 | J11: 0.00012973286 | K11: =VARP(returns!$K$2:$K$1306) -> 0.00034399108 | L11: {=TRANSPOSE(K12:K26)} -> 8.2803591e-05 | M11: 8.1554912e-05 | N11: 7.1396231e-05 | O11: 6.5066409e-05 | P11: 8.2282049e-05 | Q11: 0.00013957053 | R11: 0.00014508653 | S11: 4.6549657e-06 | T11: -2.1237873e-05 | U11: -5.408896e-06 | V11: 1.6028296e-05 | W11: 1.285452e-05 | X11: 0.0001308832 | Y11: 1.5038573e-05 | Z11: 0.00016686165
A12: KRX:000660 | B12: 1.4714791e-05 | C12: 1.1059381e-05 | D12: 2.3989106e-05 | E12: 5.0986999e-05 | F12: 2.3337907e-05 | G12: 8.1673564e-05 | H12: 9.7218918e-05 | I12: 0.00013041673 | J12: 0.00010614999 | K12: 8.2803591e-05 | L12: =VARP(returns!$L$2:$L$1306) -> 0.00060361527 | M12: {=TRANSPOSE(L13:L26)} -> 0.00015440253 | N12: 2.6680371e-05 | O12: 9.1991534e-05 | P12: 0.00018900168 | Q12: 7.7650876e-05 | R12: 9.3435612e-05 | S12: -2.0292218e-07 | T12: -1.4406363e-05 | U12: -5.1567822e-06 | V12: 1.5163793e-05 | W12: 1.4276592e-05 | X12: 5.3401337e-05 | Y12: 1.2803324e-05 | Z12: 3.8107375e-05
A13: HKG:0700 | B13: 1.0748102e-05 | C13: 4.7679797e-06 | D13: 1.8938006e-05 | E13: 6.7554604e-05 | F13: 2.205801e-05 | G13: 5.991822e-05 | H13: 6.6958869e-05 | I13: 0.00010360203 | J13: 0.00012619066 | K13: 8.1554912e-05 | L13: 0.00015440253 | M13: =VARP(returns!$M$2:$M$1306) -> 0.0006216911 | N13: {=TRANSPOSE(M14:M26)} -> 5.2241177e-06 | O13: 6.4629463e-05 | P13: 0.00041655946 | Q13: 6.9058784e-05 | R13: 8.7067495e-05 | S13: 4.1821133e-06 | T13: -7.6095458e-06 | U13: -6.7337759e-06 | V13: 2.0618248e-05 | W13: 2.6567027e-05 | X13: 4.278875e-05 | Y13: 3.7755594e-06 | Z13: 5.6531951e-05
A14: WM | B14: 4.075779e-05 | C14: 8.8020495e-05 | D14: 6.1606316e-05 | E14: 0.00010313842 | F14: 6.4535139e-05 | G14: 0.0001347943 | H14: 1.3883186e-05 | I14: 0.00010675354 | J14: 5.6281177e-05 | K14: 7.1396231e-05 | L14: 2.6680371e-05 | M14: 5.2241177e-06 | N14: =VARP(returns!$N$2:$N$1306) -> 0.00019487593 | O14: {=TRANSPOSE(N15:N26)} -> 4.7300009e-05 | P14: 3.7551395e-06 | Q14: 6.1443394e-05 | R14: 8.0037182e-05 | S14: 6.3144983e-06 | T14: -1.6083441e-05 | U14: -5.6773906e-07 | V14: 1.2404148e-05 | W14: 7.3587557e-06 | X14: 0.0001302986 | Y14: 7.5822411e-06 | Z14: 8.5743236e-05
A15: WES | B15: 3.0617108e-05 | C15: 4.0879822e-05 | D15: 4.0470468e-05 | E15: 6.4852392e-05 | F15: 4.3470019e-05 | G15: 8.6603184e-05 | H15: 5.1578492e-05 | I15: 8.8239334e-05 | J15: 4.3698589e-05 | K15: 6.5066409e-05 | L15: 9.1991534e-05 | M15: 6.4629463e-05 | N15: 4.7300009e-05 | O15: =VARP(returns!$O$2:$O$1306) -> 0.0002103234 | P15: {=TRANSPOSE(O16:O26)} -> 6.6950575e-05 | Q15: 5.2021705e-05 | R15: 6.3655757e-05 | S15: 3.5662117e-06 | T15: -1.729458e-05 | U15: -3.0724077e-06 | V15: -9.4732217e-08 | W15: 8.7324452e-06 | X15: 6.763749e-05 | Y15: 6.4267758e-06 | Z15: 5.9644113e-05
A16: HKG:1810 | B16: 1.4965405e-05 | C16: 9.9112196e-06 | D16: 1.3699139e-05 | E16: 7.0282549e-05 | F16: 2.6229703e-05 | G16: 5.5039132e-05 | H16: 7.1602226e-05 | I16: 0.00011679351 | J16: 0.00013256539 | K16: 8.2282049e-05 | L16: 0.00018900168 | M16: 0.00041655946 | N16: 3.7551395e-06 | O16: 6.6950575e-05 | P16: =VARP(returns!$P$2:$P$1306) -> 0.00081186712 | Q16: {=TRANSPOSE(P17:P26)} -> 7.9931287e-05 | R16: 9.1489698e-05 | S16: -1.9658476e-08 | T16: -2.070435e-05 | U16: -8.9585039e-06 | V16: 1.6906469e-05 | W16: 2.8385024e-05 | X16: 4.5372646e-05 | Y16: 1.098033e-05 | Z16: 5.155902e-05
A17: WOSC | B17: 3.9852615e-05 | C17: 3.8876573e-05 | D17: 6.9353461e-05 | E17: 9.0871532e-05 | F17: 7.5991006e-05 | G17: 0.00012898663 | H17: 2.9060875e-05 | I17: 0.00013320793 | J17: 0.00010440022 | K17: 0.00013957053 | L17: 7.7650876e-05 | M17: 6.9058784e-05 | N17: 6.1443394e-05 | O17: 5.2021705e-05 | P17: 7.9931287e-05 | Q17: =VARP(returns!$Q$2:$Q$1306) -> 0.0001504803 | R17: {=TRANSPOSE(Q18:Q26)} -> 9.2446612e-05 | S17: 4.4902748e-06 | T17: -1.2752817e-05 | U17: -1.1940869e-06 | V17: 7.5596228e-06 | W17: 2.2420141e-05 | X17: 0.00010186381 | Y17: 1.4782732e-05 | Z17: 0.00011557507
A18: EMXC | B18: 3.0646822e-05 | C18: 8.1033612e-05 | D18: 7.2022981e-05 | E18: 0.00015223156 | F18: 7.0955951e-05 | G18: 0.00016888238 | H18: 2.1459637e-05 | I18: 0.00025407966 | J18: 0.00011425814 | K18: 0.00014508653 | L18: 9.3435612e-05 | M18: 8.7067495e-05 | N18: 8.0037182e-05 | O18: 6.3655757e-05 | P18: 9.1489698e-05 | Q18: 9.2446612e-05 | R18: =VARP(returns!$R$2:$R$1306) -> 0.0001750782 | S18: {=TRANSPOSE(R19:R26)} -> 8.4890774e-06 | T18: -1.5561959e-05 | U18: -3.8314997e-07 | V18: 3.3366488e-05 | W18: 1.7424033e-05 | X18: 0.00014535833 | Y18: 1.5211056e-05 | Z18: 0.000150729
A19: BNDX | B19: 4.1846038e-06 | C19: 6.9911787e-06 | D19: 3.4266239e-06 | E19: 1.0228657e-05 | F19: 9.5648669e-06 | G19: 1.3075541e-06 | H19: -1.5466189e-06 | I19: 1.5814294e-05 | J19: -5.7742624e-07 | K19: 4.6549657e-06 | L19: -2.0292218e-07 | M19: 4.1821133e-06 | N19: 6.3144983e-06 | O19: 3.5662117e-06 | P19: -1.9658476e-08 | Q19: 4.4902748e-06 | R19: 8.4890774e-06 | S19: =VARP(returns!$S$2:$S$1306) -> 1.1285022e-05 | T19: {=TRANSPOSE(S20:S26)} -> 2.3637495e-05 | U19: 1.517828e-05 | V19: 9.267434e-06 | W19: -2.112242e-06 | X19: 1.4861964e-05 | Y19: -7.8879428e-06 | Z19: 9.9945426e-06
A20: TLT | B20: -5.7455601e-06 | C20: -6.9163401e-06 | D20: -1.2634194e-05 | E20: -6.9432882e-06 | F20: 1.3459996e-06 | G20: -5.8562289e-05 | H20: -5.0253266e-06 | I20: -9.0710577e-06 | J20: -2.8934172e-05 | K20: -2.1237873e-05 | L20: -1.4406363e-05 | M20: -7.6095458e-06 | N20: -1.6083441e-05 | O20: -1.729458e-05 | P20: -2.070435e-05 | Q20: -1.2752817e-05 | R20: -1.5561959e-05 | S20: 2.3637495e-05 | T20: =VARP(returns!$T$2:$T$1306) -> 0.00012257021 | U20: {=TRANSPOSE(T21:T26)} -> 4.8440238e-05 | V20: 2.7827378e-05 | W20: -1.7472486e-05 | X20: -1.6145722e-06 | Y20: -2.7561604e-05 | Z20: -2.6712854e-05
A21: VGOV | B21: 6.8891872e-06 | C21: 4.9794636e-06 | D21: 5.7500248e-07 | E21: 6.0147461e-06 | F21: 7.5817538e-06 | G21: -2.0464631e-05 | H21: -2.9643599e-06 | I21: 9.7329165e-06 | J21: -1.5046942e-05 | K21: -5.408896e-06 | L21: -5.1567822e-06 | M21: -6.7337759e-06 | N21: -5.6773906e-07 | O21: -3.0724077e-06 | P21: -8.9585039e-06 | Q21: -1.1940869e-06 | R21: -3.8314997e-07 | S21: 1.517828e-05 | T21: 4.8440238e-05 | U21: =VARP(returns!$U$2:$U$1306) -> 5.6981235e-05 | V21: {=TRANSPOSE(U22:U26)} -> 1.4584718e-05 | W21: -7.6479989e-06 | X21: 1.1300451e-05 | Y21: -1.3651516e-05 | Z21: -2.1954576e-07
A22: GLDM | B22: 3.6994821e-06 | C22: 1.7227831e-05 | D22: 1.2524477e-06 | E22: 2.4193135e-05 | F22: 1.1983582e-05 | G22: -3.9268064e-06 | H22: 6.3842807e-06 | I22: 4.6029224e-05 | J22: 3.128929e-05 | K22: 1.6028296e-05 | L22: 1.5163793e-05 | M22: 2.0618248e-05 | N22: 1.2404148e-05 | O22: -9.4732217e-08 | P22: 1.6906469e-05 | Q22: 7.5596228e-06 | R22: 3.3366488e-05 | S22: 9.267434e-06 | T22: 2.7827378e-05 | U22: 1.4584718e-05 | V22: =VARP(returns!$V$2:$V$1306) -> 9.1168573e-05 | W22: {=TRANSPOSE(V23:V26)} -> 1.7973032e-05 | X22: 2.5811799e-05 | Y22: 3.9739752e-06 | Z22: 3.6395886e-05
A23: CMOP | B23: 6.7446958e-06 | C23: 3.1564963e-06 | D23: 9.5351173e-06 | E23: -2.3178198e-06 | F23: 2.6816128e-06 | G23: 1.9094647e-05 | H23: 1.1041551e-05 | I23: 1.6759058e-05 | J23: 6.3584512e-05 | K23: 1.285452e-05 | L23: 1.4276592e-05 | M23: 2.6567027e-05 | N23: 7.3587557e-06 | O23: 8.7324452e-06 | P23: 2.8385024e-05 | Q23: 2.2420141e-05 | R23: 1.7424033e-05 | S23: -2.112242e-06 | T23: -1.7472486e-05 | U23: -7.6479989e-06 | V23: 1.7973032e-05 | W23: =VARP(returns!$W$2:$W$1306) -> 9.8108081e-05 | X23: {=TRANSPOSE(W24:W26)} -> 8.3379421e-06 | Y23: 2.0389677e-05 | Z23: 4.9171518e-05
A24: VNQ | B24: 3.3671762e-05 | C24: 0.00010568733 | D24: 8.306167e-05 | E24: 0.00016005047 | F24: 8.5732133e-05 | G24: 0.00020180609 | H24: 1.3572952e-05 | I24: 0.00021371784 | J24: 7.7501612e-05 | K24: 0.0001308832 | L24: 5.3401337e-05 | M24: 4.278875e-05 | N24: 0.0001302986 | O24: 6.763749e-05 | P24: 4.5372646e-05 | Q24: 0.00010186381 | R24: 0.00014535833 | S24: 1.4861964e-05 | T24: -1.6145722e-06 | U24: 1.1300451e-05 | V24: 2.5811799e-05 | W24: 8.3379421e-06 | X24: =VARP(returns!$X$2:$X$1306) -> 0.00025217794 | Y24: {=TRANSPOSE(X25:X26)} -> 2.9748066e-06 | Z24: 0.00014861583
A25: DBMF | B25: 1.4683639e-06 | C25: 9.0021066e-06 | D25: 1.1219087e-05 | E25: 3.328593e-06 | F25: 8.0396268e-07 | G25: 1.6179394e-05 | H25: 1.6849807e-05 | I25: 2.286905e-05 | J25: 2.3957338e-05 | K25: 1.5038573e-05 | L25: 1.2803324e-05 | M25: 3.7755594e-06 | N25: 7.5822411e-06 | O25: 6.4267758e-06 | P25: 1.098033e-05 | Q25: 1.4782732e-05 | R25: 1.5211056e-05 | S25: -7.8879428e-06 | T25: -2.7561604e-05 | U25: -1.3651516e-05 | V25: 3.9739752e-06 | W25: 2.0389677e-05 | X25: 2.9748066e-06 | Y25: =VARP(returns!$Y$2:$Y$1306) -> 7.4590158e-05 | Z25: {=TRANSPOSE(Y26)} -> 3.6098734e-05
A26: BTCGBP | B26: 4.9253007e-05 | C26: 0.00012740945 | D26: 0.00010001814 | E26: 0.00015824018 | F26: 8.4383731e-05 | G26: 0.00017433125 | H26: 6.977591e-05 | I26: 0.00039300019 | J26: 0.00012178443 | K26: 0.00016686165 | L26: 3.8107375e-05 | M26: 5.6531951e-05 | N26: 8.5743236e-05 | O26: 5.9644113e-05 | P26: 5.155902e-05 | Q26: 0.00011557507 | R26: 0.000150729 | S26: 9.9945426e-06 | T26: -2.6712854e-05 | U26: -2.1954576e-07 | V26: 3.6395886e-05 | W26: 4.9171518e-05 | X26: 0.00014861583 | Y26: 3.6098734e-05 | Z26: =VARP(returns!$Z$2:$Z$1306) -> 0.00143857

Sheet frontier
G1: port return | I1: {=MMULT(statistics!B2:Z2, TRANSPOSE(B8:Z8))} -> 0.00056344175 | K1: annual return | M1: =I1*252 -> 0.14198732
B2: rf | C2: 0.04175 | G2: port var | I2: {=MMULT(MMULT(B8:Z8,covariances!B2:Z26), TRANSPOSE(frontier!B8:Z8))} -> 7.5586585e-05 | O2: annual sharpe | Q2: =(M1-C2)/M3 -> 0.72628457
C3: =C2/252 -> 0.0001656746 | G3: portfolio std | I3: =SQRT(I2) -> 0.0086940546 | K3: annual vol | M3: =I3*SQRT(252) -> 0.13801384
G4: sharpe | I4: =(I1-C3)/I3 -> 0.045751627
B6: {=_xlfn.RANDARRAY(1,25,0,1)} -> 0.10113786 | C6: 0.15035789 | D6: 0.65419732 | E6: 0.75060196 | F6: 0.30766178 | G6: 0.5313195 | H6: 0.31373077 | I6: 0.93946451 | J6: 0.50324777 | K6: 0.82772633 | L6: 0.97933401 | M6: 0.66184097 | N6: 0.44916477 | O6: 0.54740289 | P6: 0.062180417 | Q6: 0.85339734 | R6: 0.83811377 | S6: 0.8063964 | T6: 0.76329854 | U6: 0.5420727 | V6: 0.84521709 | W6: 0.6238879 | X6: 0.077464186 | Y6: 0.0096322538 | Z6: 0.68620449 | AA6: =SUM(B6:Z6) -> 13.825053
B7: AZN | C7: COST | D7: DTE | E7: RACE | F7: IBE | G7: JPM | H7: TYO:7974 | I7: NVDA | J7: RIO | K7: SIE | L7: KRX:000660 | M7: HKG:0700 | N7: WM | O7: WES | P7: HKG:1810 | Q7: WOSC | R7: EMXC | S7: BNDX | T7: TLT | U7: VGOV | V7: GLDM | W7: CMOP | X7: VNQ | Y7: DBMF | Z7: BTCGBP
B8: =B6/$AA$6 -> 0.0073155492 | C8: =C6/$AA$6 -> 0.010875755 | D8: =D6/$AA$6 -> 0.047319696 | E8: =E6/$AA$6 -> 0.054292879 | F8: =F6/$AA$6 -> 0.02225393 | G8: =G6/$AA$6 -> 0.038431642 | H8: =H6/$AA$6 -> 0.022692916 | I8: =I6/$AA$6 -> 0.067953771 | ... Z8: =Z6/$AA$6 -> 0.049634852
B10: sum of w | D10: =SUM(B8:Z8) -> 1 | S10: risk | T10: return
G11: mu | H11: sigma | R11: trials | S11: =M3 -> 0.13801384 | T11: =M1 -> 0.14198732
R12: 1 | S12: 0.12057212 | T12: 0.13163794
R13: 2 | S13: 0.13886361 | T13: 0.14607541
R14: 3 | S14: 0.13348853 | T14: 0.15791439
R15: 4 | S15: 0.12136762 | T15: 0.120658
H16: cml | R16: 5 | S16: 0.1481214 | T16: 0.14063545
H17: 0 | I17: =C2 -> 0.04175 | R17: 6 | S17: 0.15246311 | T17: 0.17836315
H18: 0.141046 | I18: 0.234084 | R18: 7 | S18: 0.13523852 | T18: 0.15085203
R19: 8 | S19: 0.13888216 | T19: 0.16248051
R20: 9 | S20: 0.12475872 | T20: 0.1219017
R21: 10 | S21: 0.121361 | T21: 0.12540669
R22: 11 | S22: 0.12482122 | T22: 0.13909428
R23: 12 | S23: 0.12996836 | T23: 0.13046251
R24: 13 | S24: 0.13515236 | T24: 0.14335249
R25: 14 | S25: 0.14627201 | T25: 0.14037291
R26: 15 | S26: 0.13441343 | T26: 0.13725321
R27: 16 | S27: 0.11575273 | T27: 0.12099467
R28: 17 | S28: 0.14117564 | T28: 0.14836259
R29: 18 | S29: 0.14699064 | T29: 0.14190914
R30: 19 | S30: 0.12653205 | T30: 0.12974027
... R10011: 10000 | S10011: 0.11991356 | T10011: 0.12759089

Sheet constrained
F1: port return | H1: {=MMULT(statistics!B2:Z2, TRANSPOSE(A8:Y8))} -> 0.00068880041 | J1: annual return | L1: =H1*252 -> 0.1735777
A2: rf | B2: 0.04175 | F2: port var | H2: {=MMULT(MMULT(A8:Y8,covariances!B2:Z26), TRANSPOSE(A8:Y8))} -> 5.5481631e-05 | N2: annual sharpe | P2: =(L1-B2)/L3 -> 1.1148895
B3: =B2/252 -> 0.0001656746 | F3: portfolio std | H3: =SQRT(H2) -> 0.0074485992 | J3: annual vol | L3: =H3*SQRT(252) -> 0.11824285
F4: sharpe | H4: =(H1-B3)/H3 -> 0.070231434
A7: AZN | B7: COST | C7: DTE | D7: RACE | E7: IBE | F7: JPM | G7: TYO:7974 | H7: NVDA | I7: RIO | J7: SIE | K7: KRX:000660 | L7: HKG:0700 | M7: WM | N7: WES | O7: HKG:1810 | P7: WOSC | Q7: EMXC | R7: BNDX | S7: TLT | T7: VGOV | U7: GLDM | V7: CMOP | W7: VNQ | X7: DBMF | Y7: BTCGBP
A8: 0.077876775 | B8: 0.12211813 | C8: 0.12211813 | D8: 0.010168862 | E8: 0 | F8: 0 | G8: 0.024835106 | H8: 0.065854567 | I8: 0 | J8: 0.016985897 | K8: 0 | L8: 0 | M8: 0.073885864 | N8: 0.065318836 | O8: 0.031428459 | P8: 0 | Q8: 0 | R8: 0.15 | S8: 0 | T8: 0 | U8: 0.1240396 | V8: 0.061392645 | W8: 0 | X8: 0 | Y8: 0.053977119
A10: sum of w | C10: =SUM(A8:Y8) -> 1
H13: equity w | I13: fixed income w | J13: alternatives w
H14: =SUM(A8:Q8) -> 0.61059063 | I14: =SUM(R8:T8) -> 0.15 | J14: =SUM(U8:Y8) -> 0.23940937
E16: industrials | F16: materials | G16: health | H16: tech | I16: comms | J16: util | K16: cyclicals | L16: non cycl | M16: business services | N16: financials
C17: total eq | E17: =SUM(J8) -> 0.016985897 | F17: =SUM(I8) -> 0 | G17: =SUM(A8) -> 0.077876775 | H17: =SUM(G8+H8+O8+L8+K8) -> 0.12211813 | I17: =SUM(C8) -> 0.12211813 | J17: =SUM(E8) -> 0 | K17: =SUM(D8+N8) -> 0.075487699 | L17: =SUM(B8) -> 0.12211813 | M17: =SUM(M8) -> 0.073885864 | N17: =SUM(F8) -> 0
C18: =SUM(E17:N17) -> 0.61059063 | E18: =E17/C18 -> 0.027818797 | F18: =F17/C18 -> 0 | G18: =G17/C18 -> 0.12754335 | H18: =H17/C18 -> 0.20000001 | I18: =I17/C18 -> 0.20000001 | J18: =J17/C18 -> 0 | K18: =K17/C18 -> 0.12363062 | L18: =L17/C18 -> 0.20000001 | M18: =M17/C18 -> 0.1210072 | N18: =N17/C18 -> 0

Sheet tangency
F1: port return | H1: {=MMULT(statistics!B2:Z2, TRANSPOSE(A8:Y8))} -> 0.00092837447 | J1: annual return | L1: =H1*252 -> 0.23395037
A2: rf | B2: 0.04175 | F2: port var | H2: {=MMULT(MMULT(A8:Y8,covariances!B2:Z26), TRANSPOSE(A8:Y8))} -> 7.8833466e-05 | N2: annual sharpe | P2: =(L1-B2)/L3 -> 1.3636365
B3: =B2/252 -> 0.0001656746 | F3: portfolio std | H3: =SQRT(H2) -> 0.0088788212 | J3: annual vol | L3: =H3*SQRT(252) -> 0.14094692
F4: sharpe | H4: =(H1-B3)/H3 -> 0.085901028
A7: AZN | B7: COST | C7: DTE | D7: RACE | E7: IBE | F7: JPM | G7: TYO:7974 | H7: NVDA | I7: RIO | J7: SIE | K7: KRX:000660 | L7: HKG:0700 | M7: WM | N7: WES | O7: HKG:1810 | P7: WOSC | Q7: EMXC | R7: BNDX | S7: TLT | T7: VGOV | U7: GLDM | V7: CMOP | W7: VNQ | X7: DBMF | Y7: BTCGBP
A8: 0.019386688 | B8: 0.21067254 | C8: 0.12430822 | D8: 0 | E8: 0 | F8: 0 | G8: 0.1670612 | H8: 0.09627423 | I8: 0 | J8: 0 | K8: 0 | L8: 0 | M8: 0 | N8: 0 | O8: 0.074102537 | P8: 0 | Q8: 0 | R8: 0 | S8: 0 | T8: 0 | U8: 0.16845861 | V8: 0.098032955 | W8: 0 | X8: 0 | Y8: 0.041703026
A10: sum of w | C10: =SUM(A8:Y8) -> 1
H13: equity w | I13: fixed income w | J13: alternatives w
H14: =SUM(A8:Q8) -> 0.69180542 | I14: =SUM(R8:T8) -> 0 | J14: =SUM(U8:Y8) -> 0.30819459
E16: industrials | F16: materials | G16: health | H16: tech | I16: comms | J16: util | K16: cyclicals | L16: non cycl | M16: business services | N16: financials
C17: total eq | E17: =SUM(J8) -> 0 | F17: =SUM(I8) -> 0 | G17: =SUM(A8) -> 0.019386688 | H17: =SUM(G8+H8+O8+L8+K8) -> 0.33743797 | I17: =SUM(C8) -> 0.12430822 | J17: =SUM(E8) -> 0 | K17: =SUM(D8+N8) -> 0 | L17: =SUM(B8) -> 0.21067254 | M17: =SUM(M8) -> 0 | N17: =SUM(F8) -> 0
C18: =SUM(E17:N17) -> 0.69180542 | E18: =E17/C18 -> 0 | F18: =F17/C18 -> 0 | G18: =G17/C18 -> 0.028023324 | H18: =H17/C18 -> 0.48776427 | I18: =I17/C18 -> 0.17968668 | J18: =J17/C18 -> 0 | K18: =K17/C18 -> 0 | L18: =L17/C18 -> 0.30452572 | M18: =M17/C18 -> 0 | N18: =N17/C18 -> 0
